has_blue_color/__init__.py
has_blue_color/detector.py
has_blue_color-1.0.0.dist-info/METADATA
has_blue_color-1.0.0.dist-info/WHEEL
has_blue_color-1.0.0.dist-info/top_level.txt
has_blue_color-1.0.0.dist-info/RECORD
