Metadata-Version: 2.4
Name: has-blue-color
Version: 1.0.0
Summary: Detecta si una imagen contiene color azul usando OpenCV
Author-email: Juan Rey <sudo.delete.evil@gmail.com>
License: MIT
Requires-Python: >=3.10
Requires-Dist: numpy==2.2.3
Requires-Dist: opencv-python==4.11.0.86
